adv_math_captcha/__init__.py
adv_math_captcha/captcha.py
adv_math_captcha/generate.py
adv_math_captcha_ostrichb-0.9.10.dist-info/LICENSE.txt
adv_math_captcha_ostrichb-0.9.10.dist-info/METADATA
adv_math_captcha_ostrichb-0.9.10.dist-info/WHEEL
adv_math_captcha_ostrichb-0.9.10.dist-info/top_level.txt
adv_math_captcha_ostrichb-0.9.10.dist-info/RECORD
