Metadata-Version: 2.1
Name: adv-math-captcha-ostrichb
Version: 0.9.10
Summary: Advanced mathematical captcha generator and 
Home-page: https://github.com/Ostrichbeta/adv-math-captcha
Author: Ostrichbeta
Author-email: ostrichb@yandex.com
License: UNKNOWN
Project-URL: Bug Tracker, https://github.com/Ostrichbeta/adv-math-captcha/issues
Platform: UNKNOWN
Classifier: Programming Language :: Python :: 3
Classifier: Development Status :: 4 - Beta
Classifier: License :: OSI Approved :: MIT License
Classifier: Operating System :: OS Independent
Requires-Python: >=3.8
License-File: LICENSE.txt
Requires-Dist: sympy (>=1.9)
